atorvi/__init__.py
atorvi/atomic_orbitals.py
atorvi/atorvi.py
atorvi-0.1.1.dist-info/LICENSE
atorvi-0.1.1.dist-info/METADATA
atorvi-0.1.1.dist-info/WHEEL
atorvi-0.1.1.dist-info/entry_points.txt
atorvi-0.1.1.dist-info/top_level.txt
atorvi-0.1.1.dist-info/RECORD
