Metadata-Version: 2.1
Name: atorvi
Version: 0.1.1
Summary: Package for visualizing atomic orbitals
Author-email: Dmitry Korotin <dmitry@korotin.name>
License: MIT
Project-URL: Homepage, https://github.com/dkorotin/atorvi
Keywords: atomic orbitals,visualization
Classifier: Programming Language :: Python :: 3
Classifier: License :: OSI Approved :: MIT License
Classifier: Operating System :: OS Independent
Requires-Python: >=3.6
License-File: LICENSE
Requires-Dist: numpy
Requires-Dist: scipy
Provides-Extra: pymatgen
Requires-Dist: pymatgen; extra == "pymatgen"
